ledgerlinker/__init__.py
ledgerlinker/client.py
ledgerlinker/update_tracker.py
ledgerlinker/providers/__init__.py
ledgerlinker/providers/adp.py
ledgerlinker/providers/base.py
ledgerlinker/providers/ledgerlinker_service.py
ledgerlinker/providers/prosper.py
ledgerlinker/providers/tests/__init__.py
ledgerlinker/providers/tests/test_base.py
ledgerlinker/providers/tests/test_ledgerlinker_service.py
ledgerlinker/providers/tests/test_prosper.py
ledgerlinker-1.1.0.dist-info/METADATA
ledgerlinker-1.1.0.dist-info/WHEEL
ledgerlinker-1.1.0.dist-info/entry_points.txt
ledgerlinker-1.1.0.dist-info/top_level.txt
ledgerlinker-1.1.0.dist-info/RECORD
